markdownexporter/__init__.py
markdownexporter/plugin.py
markdownexporter-0.1.9.dist-info/METADATA
markdownexporter-0.1.9.dist-info/WHEEL
markdownexporter-0.1.9.dist-info/entry_points.txt
markdownexporter-0.1.9.dist-info/top_level.txt
markdownexporter-0.1.9.dist-info/RECORD
