Metadata-Version: 2.4
Name: markdownexporter
Version: 0.1.9
Summary: Add your description here
License: MIT
Classifier: Programming Language :: Python :: 3
Classifier: License :: OSI Approved :: MIT License
Classifier: Operating System :: OS Independent
Classifier: Framework :: MkDocs
Requires-Python: >=3.9
Requires-Dist: mkdocs>=1.4.1
Requires-Dist: toml>=0.10.2
